fastpage/__init__.py
fastpage/app.py
fastpage/components/__init__.py
fastpage/components/alert.py
fastpage/components/button.py
fastpage/components/layout.py
fastpage/components/link.py
fastpage/components/toast.py
fastpage/config.py
fastpage/middlewares.py
fastpage/responses.py
fastpage/utils/__init__.py
fastpage/utils/module_loading.py
fastpage/utils/versioned_static.py
fastpage-0.1.0.dist-info/METADATA
fastpage-0.1.0.dist-info/WHEEL
fastpage-0.1.0.dist-info/RECORD
